lattifai/__init__.py
lattifai/audio2.py
lattifai/client.py
lattifai/errors.py
lattifai/logging.py
lattifai/mixin.py
lattifai/types.py
lattifai/utils.py
lattifai/alignment/__init__.py
lattifai/alignment/lattice1_aligner.py
lattifai/alignment/lattice1_worker.py
lattifai/alignment/phonemizer.py
lattifai/alignment/punctuation.py
lattifai/alignment/segmenter.py
lattifai/alignment/sentence_splitter.py
lattifai/alignment/text_align.py
lattifai/alignment/tokenizer.py
lattifai/caption/__init__.py
lattifai/caption/caption.py
lattifai/caption/standardize.py
lattifai/caption/supervision.py
lattifai/caption/utils.py
lattifai/caption/formats/__init__.py
lattifai/caption/formats/base.py
lattifai/caption/formats/gemini.py
lattifai/caption/formats/json.py
lattifai/caption/formats/lrc.py
lattifai/caption/formats/pysubs2.py
lattifai/caption/formats/sbv.py
lattifai/caption/formats/tabular.py
lattifai/caption/formats/textgrid.py
lattifai/caption/formats/ttml.py
lattifai/caption/formats/vtt.py
lattifai/caption/formats/nle/__init__.py
lattifai/caption/formats/nle/audition.py
lattifai/caption/formats/nle/avid.py
lattifai/caption/formats/nle/fcpxml.py
lattifai/caption/formats/nle/premiere.py
lattifai/caption/parsers/__init__.py
lattifai/caption/parsers/text_parser.py
lattifai/cli/__init__.py
lattifai/cli/alignment.py
lattifai/cli/caption.py
lattifai/cli/diarization.py
lattifai/cli/transcribe.py
lattifai/cli/youtube.py
lattifai/config/__init__.py
lattifai/config/alignment.py
lattifai/config/caption.py
lattifai/config/client.py
lattifai/config/diarization.py
lattifai/config/media.py
lattifai/config/transcription.py
lattifai/diarization/__init__.py
lattifai/diarization/lattifai.py
lattifai/transcription/__init__.py
lattifai/transcription/base.py
lattifai/transcription/gemini.py
lattifai/transcription/lattifai.py
lattifai/transcription/prompts/README.md
lattifai/transcription/prompts/__init__.py
lattifai/transcription/prompts/gemini/README.md
lattifai-1.2.2.dist-info/licenses/LICENSE
lattifai-1.2.2.dist-info/METADATA
lattifai-1.2.2.dist-info/WHEEL
lattifai-1.2.2.dist-info/entry_points.txt
lattifai-1.2.2.dist-info/top_level.txt
lattifai-1.2.2.dist-info/RECORD
