Metadata-Version: 2.4
Name: lattifai
Version: 1.2.2
Summary: Lattifai Python SDK: Seamless Integration with Lattifai's Speech and Video AI Services
Author-email: Lattifai Technologies <tech@lattifai.com>
Maintainer-email: Lattice <tech@lattifai.com>
License: MIT License
Project-URL: Homepage, https://github.com/lattifai/lattifai-python
Project-URL: Documentation, https://github.com/lattifai/lattifai-python/blob/main/README.md
Project-URL: Bug Tracker, https://github.com/lattifai/lattifai-python/issues
Project-URL: Discussions, https://github.com/lattifai/lattifai-python/discussions
Project-URL: Changelog, https://github.com/lattifai/lattifai-python/blob/main/CHANGELOG.md
Keywords: lattifai,speech recognition,video analysis,ai,sdk,api client
Classifier: Development Status :: 5 - Production/Stable
Classifier: Intended Audience :: Developers
Classifier: Intended Audience :: Science/Research
Classifier: License :: OSI Approved :: Apache Software License
Classifier: Programming Language :: Python :: 3.10
Classifier: Programming Language :: Python :: 3.11
Classifier: Programming Language :: Python :: 3.12
Classifier: Programming Language :: Python :: 3.13
Classifier: Programming Language :: Python :: 3.14
Classifier: Operating System :: MacOS :: MacOS X
Classifier: Operating System :: POSIX :: Linux
Classifier: Operating System :: Microsoft :: Windows
Classifier: Topic :: Multimedia :: Sound/Audio
Classifier: Topic :: Multimedia :: Video
Classifier: Topic :: Scientific/Engineering :: Artificial Intelligence
Requires-Python: <3.15,>=3.10
License-File: LICENSE
Requires-Dist: lattifai[core]
Requires-Dist: lattifai[alignment]
Requires-Dist: lattifai[transcription]
Requires-Dist: lattifai[workflow]
Requires-Dist: lattifai[server]
Provides-Extra: core
Requires-Dist: k2py>=0.2.1; extra == "core"
Requires-Dist: lattifai-core>=0.6.0; extra == "core"
Requires-Dist: lattifai-run>=1.0.1; extra == "core"
Requires-Dist: python-dotenv; extra == "core"
Requires-Dist: msgpack; extra == "core"
Requires-Dist: scipy!=1.16.3; extra == "core"
Requires-Dist: av; extra == "core"
Provides-Extra: alignment
Requires-Dist: lhotse>=1.26.0; extra == "alignment"
Requires-Dist: colorful>=0.5.6; extra == "alignment"
Requires-Dist: pysubs2; extra == "alignment"
Requires-Dist: praatio; extra == "alignment"
Requires-Dist: tgt; extra == "alignment"
Requires-Dist: onnx>=1.16.0; extra == "alignment"
Requires-Dist: onnxruntime; extra == "alignment"
Requires-Dist: g2p-phonemizer>=0.4.0; extra == "alignment"
Requires-Dist: wtpsplit>=2.1.7; extra == "alignment"
Requires-Dist: modelscope>=1.33.0; extra == "alignment"
Requires-Dist: error-align-fix>=0.1.4; extra == "alignment"
Provides-Extra: transcription
Requires-Dist: OmniSenseVoice>=0.4.2; extra == "transcription"
Requires-Dist: nemo_toolkit_asr[asr]>=2.7.0rc4; extra == "transcription"
Requires-Dist: google-genai>=1.22.0; extra == "transcription"
Requires-Dist: pyannote-audio-notorchdeps>=4.0.2; extra == "transcription"
Provides-Extra: workflow
Requires-Dist: questionary>=2.0; extra == "workflow"
Requires-Dist: yt-dlp; extra == "workflow"
Requires-Dist: pycryptodome; extra == "workflow"
Provides-Extra: server
Requires-Dist: fastapi>=0.111.0; extra == "server"
Requires-Dist: uvicorn>=0.30.0; extra == "server"
Requires-Dist: python-multipart>=0.0.9; extra == "server"
Requires-Dist: jinja2>=3.1.4; extra == "server"
Provides-Extra: dev
Requires-Dist: pytest>=8.0.0; extra == "dev"
Requires-Dist: pytest-cov>=4.1.0; extra == "dev"
Requires-Dist: pytest-asyncio>=0.23.0; extra == "dev"
Dynamic: license-file
